odoo/addons/account_invoice_margin/README.rst
odoo/addons/account_invoice_margin/__init__.py
odoo/addons/account_invoice_margin/__manifest__.py
odoo/addons/account_invoice_margin/hooks.py
odoo/addons/account_invoice_margin/data/res_groups.xml
odoo/addons/account_invoice_margin/i18n/account_invoice_margin.pot
odoo/addons/account_invoice_margin/i18n/es.po
odoo/addons/account_invoice_margin/i18n/fi.po
odoo/addons/account_invoice_margin/i18n/fr.po
odoo/addons/account_invoice_margin/i18n/it.po
odoo/addons/account_invoice_margin/i18n/pt.po
odoo/addons/account_invoice_margin/i18n/pt_BR.po
odoo/addons/account_invoice_margin/models/__init__.py
odoo/addons/account_invoice_margin/models/account_invoice.py
odoo/addons/account_invoice_margin/readme/CONTRIBUTORS.rst
odoo/addons/account_invoice_margin/readme/DESCRIPTION.rst
odoo/addons/account_invoice_margin/readme/USAGE.rst
odoo/addons/account_invoice_margin/report/__init__.py
odoo/addons/account_invoice_margin/report/account_invoice_report.py
odoo/addons/account_invoice_margin/security/account_invoice_margin_security.xml
odoo/addons/account_invoice_margin/static/description/account_invoice_form.png
odoo/addons/account_invoice_margin/static/description/account_invoice_form_tree.png
odoo/addons/account_invoice_margin/static/description/icon.png
odoo/addons/account_invoice_margin/static/description/index.html
odoo/addons/account_invoice_margin/tests/__init__.py
odoo/addons/account_invoice_margin/tests/test_account_invoice_margin.py
odoo/addons/account_invoice_margin/views/account_invoice_margin_view.xml
odoo12_addon_account_invoice_margin-12.0.3.0.3.dist-info/METADATA
odoo12_addon_account_invoice_margin-12.0.3.0.3.dist-info/WHEEL
odoo12_addon_account_invoice_margin-12.0.3.0.3.dist-info/top_level.txt
odoo12_addon_account_invoice_margin-12.0.3.0.3.dist-info/RECORD
